google_flights/__init__.py
google_flights/google_flights.py
google_flights_scraper-0.1.0.dist-info/LICENSE
google_flights_scraper-0.1.0.dist-info/METADATA
google_flights_scraper-0.1.0.dist-info/WHEEL
google_flights_scraper-0.1.0.dist-info/entry_points.txt
google_flights_scraper-0.1.0.dist-info/top_level.txt
google_flights_scraper-0.1.0.dist-info/RECORD
