Metadata-Version: 2.1
Name: google_flights_scraper
Version: 0.1.0
Summary: A Python package to scrape flight data from Google Flights.
Home-page: https://github.com/yourusername/google_flights_scraper
Author: Hugo Gonçalves
Author-email: hugoglvs@icloud.com
Keywords: google flights scraper,google flights,flights scraper,flights
Classifier: Development Status :: 3 - Alpha
Classifier: Intended Audience :: Developers
Classifier: Topic :: Software Development :: Build Tools
Classifier: License :: OSI Approved :: MIT License
Classifier: Programming Language :: Python :: 3
Classifier: Programming Language :: Python :: 3.8
Classifier: Programming Language :: Python :: 3.9
Classifier: Programming Language :: Python :: 3.10
Classifier: Programming Language :: Python :: 3.11
Classifier: Operating System :: OS Independent
Requires-Python: >=3.8
License-File: LICENSE
Requires-Dist: playwright >=1.42
Requires-Dist: selectolax >=0.3
Requires-Dist: click >=8.1
